authkit_token/__init__.py
authkit_token/api.py
authkit_token/client.py
authkit_token/py.typed
authkit_token/types.py
authkit_token/utils.py
authkit_token-1.0.1.dist-info/licenses/LICENSE
authkit_token-1.0.1.dist-info/METADATA
authkit_token-1.0.1.dist-info/WHEEL
authkit_token-1.0.1.dist-info/top_level.txt
authkit_token-1.0.1.dist-info/RECORD
